{"name":"jsdeliver","slug":"jsdeliver","count":1,"postlist":[{"title":"hexo + jsdeliver配置","uid":"ec3f56e1d7e823a5cde500ee82bbce7e","slug":"3_hexo和jsdeliver配置","date":"2023-05-05T05:50:17.266Z","updated":"2024-11-14T07:22:37.478Z","comments":true,"path":"api/articles/3_hexo和jsdeliver配置.json","keywords":null,"cover":"https://cdn.jsdelivr.net/gh/nanguawuming/CDN@1.0/picture/3.jpg","text":"hexo常用命令hexo clean # 清理缓存文件 hexo g # 生成静态文件到public文件夹 hexo s # 本地预览 hexo d # 上传部署到仓库 jsdeliver配置图片加载有点慢，尝试使用jsdeliver搭建CDN 可以参考：https://zhua...","link":"","photos":[],"count_time":{"symbolsCount":554,"symbolsTime":"1 mins."},"categories":[{"name":"工具","slug":"工具","count":7,"path":"api/categories/工具.json"}],"tags":[{"name":"jsdeliver","slug":"jsdeliver","count":1,"path":"api/tags/jsdeliver.json"}],"author":{"name":"南瓜の无名","slug":"blog-author","avatar":"../picture/head_01.jpg","link":"/","description":"你不需要很厉害才能开始，但你需要开始才能变得很厉害！","socials":{"github":"","twitter":"","stackoverflow":"","wechat":"","qq":"","weibo":"","zhihu":"","csdn":"","juejin":"","customs":{}}},"feature":false}]}