[{"name":"8086汇编","path":"api/tags/8086汇编.json","slug":"8086汇编","count":8},{"name":"c语言基础","path":"api/tags/c语言基础.json","slug":"c语言基础","count":2},{"name":"ssti模板注入","path":"api/tags/ssti模板注入.json","slug":"ssti模板注入","count":2},{"name":"test","path":"api/tags/test.json","slug":"test","count":1},{"name":"pwn","path":"api/tags/pwn.json","slug":"pwn","count":2},{"name":"Kali","path":"api/tags/Kali.json","slug":"Kali","count":1},{"name":"LitCTF","path":"api/tags/LitCTF.json","slug":"LitCTF","count":1},{"name":"wp","path":"api/tags/wp.json","slug":"wp","count":1},{"name":"vim","path":"api/tags/vim.json","slug":"vim","count":1},{"name":"渗透工具","path":"api/tags/渗透工具.json","slug":"渗透工具","count":4},{"name":"杂项","path":"api/tags/杂项.json","slug":"杂项","count":3},{"name":"wireshark","path":"api/tags/wireshark.json","slug":"wireshark","count":1},{"name":"随想","path":"api/tags/随想.json","slug":"随想","count":1}]